extraasync/__init__.py
extraasync/aenumerate.py
extraasync/async_hooks.py
extraasync/sync_async_bridge.py
extraasync/taskgroup.py
extraasync-0.3.0.dist-info/LICENSE
extraasync-0.3.0.dist-info/METADATA
extraasync-0.3.0.dist-info/WHEEL
extraasync-0.3.0.dist-info/top_level.txt
extraasync-0.3.0.dist-info/RECORD
